tp_llmatch_formatter/__init__.py
tp_llmatch_formatter/main.py
tp_llmatch_formatter/prompts.py
tp_llmatch_formatter-2025.12.21170024.dist-info/METADATA
tp_llmatch_formatter-2025.12.21170024.dist-info/WHEEL
tp_llmatch_formatter-2025.12.21170024.dist-info/top_level.txt
tp_llmatch_formatter-2025.12.21170024.dist-info/RECORD
