Metadata-Version: 2.4
Name: tp-llmatch-formatter
Version: 2025.12.21170024
Summary: A new package designed to streamline content management tasks within Textpattern CMS 4.9.0. It allows users to input text-based content or instructions related to their CMS, such as article drafts, fo
Author-email: tp-llmatch-formatter <hi@eugene.plus>
License: MIT
Project-URL: Homepage, https://github.com/chigwell/tp-llmatch-formatter
Requires-Python: >=3.9
Requires-Dist: langchain-llm7>=0.0.0
Requires-Dist: llmatch-messages>=0.0.0
Requires-Dist: langchain-core>=0.3.0
